import_ipynb.py
import_ipynb-0.2.dist-info/LICENSE.txt
import_ipynb-0.2.dist-info/METADATA
import_ipynb-0.2.dist-info/WHEEL
import_ipynb-0.2.dist-info/top_level.txt
import_ipynb-0.2.dist-info/RECORD
